keywordsai_exporter_haystack/__init__.py
keywordsai_exporter_haystack/connector.py
keywordsai_exporter_haystack/gateway.py
keywordsai_exporter_haystack/logger.py
keywordsai_exporter_haystack/tracer.py
keywordsai_exporter_haystack-0.1.1.dist-info/licenses/LICENSE
keywordsai_exporter_haystack-0.1.1.dist-info/METADATA
keywordsai_exporter_haystack-0.1.1.dist-info/WHEEL
keywordsai_exporter_haystack-0.1.1.dist-info/RECORD
