Metadata-Version: 2.4
Name: keywordsai-exporter-haystack
Version: 0.1.1
Summary: Keywords AI integration for Haystack pipelines with tracing and logging support
License: MIT
License-File: LICENSE
Keywords: haystack,keywords-ai,llm,observability,tracing,monitoring
Author: Keywords AI
Author-email: team@keywordsai.co
Requires-Python: >=3.9,<4.0
Classifier: License :: OSI Approved :: MIT License
Classifier: Programming Language :: Python :: 3
Classifier: Programming Language :: Python :: 3.9
Classifier: Programming Language :: Python :: 3.10
Classifier: Programming Language :: Python :: 3.11
Classifier: Programming Language :: Python :: 3.12
Classifier: Programming Language :: Python :: 3.13
Classifier: Programming Language :: Python :: 3.14
Requires-Dist: haystack-ai (>=2.0.0,<3.0.0)
Requires-Dist: requests (>=2.31.0,<3.0.0)
Project-URL: Documentation, https://docs.keywordsai.co
Project-URL: Homepage, https://keywordsai.co
Project-URL: Repository, https://github.com/Keywords-AI/keywordai_sdks
